{
  "assessmentCollection": [
    {
      "id": "09cec7cb-ddfe-4f5d-ac2b-cd7d24b26c9c",
      "memberid": "3ad52697-6d98-4d80-8273-084de55a86c0",
      "date": "8/20/2019, 12:54:54 PM",
      "weight": "25",
      "chest": "",
      "thigh": "",
      "upperarm": "",
      "waist": "",
      "hip": "",
      "trend": true
    },
    {
      "id": "6d558c32-68e2-4dc8-b514-525199fe0f2d",
      "memberid": "3ad52697-6d98-4d80-8273-084de55a86c0",
      "date": "8/20/2019, 12:55:04 PM",
      "weight": "200",
      "chest": "",
      "thigh": "",
      "upperarm": "",
      "waist": "",
      "hip": "",
      "trend": false
    },
    {
      "id": "9294bd6e-2ef8-44e0-8932-c52ffb31bd4b",
      "memberid": "3ad52697-6d98-4d80-8273-084de55a86c0",
      "date": "8/20/2019, 1:00:30 PM",
      "weight": "30",
      "chest": "",
      "thigh": "",
      "upperarm": "",
      "waist": "",
      "hip": "",
      "trend": true
    },
    {
      "id": "6b416de9-9783-42c7-9134-a9bd3145b80f",
      "memberid": "3ad52697-6d98-4d80-8273-084de55a86c0",
      "date": "8/20/2019, 1:11:03 PM",
      "weight": "50",
      "chest": "",
      "thigh": "",
      "upperarm": "",
      "waist": "",
      "hip": "",
      "trend": false
    },
    {
      "id": "996b564b-e5fc-407f-af49-02433af5a868",
      "memberid": "3ad52697-6d98-4d80-8273-084de55a86c0",
      "date": "8/20/2019, 1:11:14 PM",
      "weight": "60",
      "chest": "",
      "thigh": "",
      "upperarm": "",
      "waist": "",
      "hip": "",
      "trend": false
    },
    {
      "id": "5810c93d-ada8-45f7-9c8c-ddbef7b07a5c",
      "memberid": "3ad52697-6d98-4d80-8273-084de55a86c0",
      "date": "8/20/2019, 1:11:26 PM",
      "weight": "65",
      "chest": "",
      "thigh": "",
      "upperarm": "",
      "waist": "",
      "hip": "",
      "trend": false
    },
    {
      "id": "ebaadc76-2e63-4b60-a65f-52581ba0d7f3",
      "memberid": "3ad52697-6d98-4d80-8273-084de55a86c0",
      "date": "8/20/2019, 1:11:37 PM",
      "weight": "70",
      "chest": "",
      "thigh": "",
      "upperarm": "",
      "waist": "",
      "hip": "",
      "trend": false
    },
    {
      "id": "2defbd1c-a934-4d51-b93f-761ad3a8cd4a",
      "memberid": "3ad52697-6d98-4d80-8273-084de55a86c0",
      "date": "8/20/2019, 1:15:35 PM",
      "weight": "79.5",
      "chest": "",
      "thigh": "",
      "upperarm": "",
      "waist": "",
      "hip": "",
      "trend": false
    },
    {
      "id": "c2b80ff8-54c3-427e-9448-9d4338fad6ef",
      "memberid": "3ad52697-6d98-4d80-8273-084de55a86c0",
      "date": "8/20/2019, 1:19:35 PM",
      "weight": "80",
      "chest": "",
      "thigh": "",
      "upperarm": "",
      "waist": "",
      "hip": "",
      "trend": false
    },
    {
      "id": "eb3aa7a6-779c-4ca7-958e-eed55605f7f8",
      "memberid": "3ad52697-6d98-4d80-8273-084de55a86c0",
      "date": "8/20/2019, 1:20:39 PM",
      "weight": "70.02",
      "chest": "",
      "thigh": "",
      "upperarm": "",
      "waist": "",
      "hip": "",
      "trend": true
    },
    {
      "id": "1a72f94a-72d6-4b9f-9a48-d1eec7d0d349",
      "memberid": "3ad52697-6d98-4d80-8273-084de55a86c0",
      "date": "8/20/2019, 1:21:04 PM",
      "weight": "75.02",
      "chest": "",
      "thigh": "",
      "upperarm": "",
      "waist": "",
      "hip": "",
      "trend": false
    },
    {
      "id": "04340f38-1b5a-4142-addb-5a446b8db478",
      "memberid": "3ad52697-6d98-4d80-8273-084de55a86c0",
      "date": "8/20/2019, 1:21:17 PM",
      "weight": "77",
      "chest": "",
      "thigh": "",
      "upperarm": "",
      "waist": "",
      "hip": "",
      "trend": false
    },
    {
      "id": "f961a7d5-dec6-4986-90a1-524d4e01caed",
      "memberid": "3ad52697-6d98-4d80-8273-084de55a86c0",
      "date": "8/20/2019, 1:21:23 PM",
      "weight": "73",
      "chest": "",
      "thigh": "",
      "upperarm": "",
      "waist": "",
      "hip": "",
      "trend": true
    },
    {
      "id": "b524231a-9e02-40da-8be4-82cd4604ec29",
      "memberid": "3ad52697-6d98-4d80-8273-084de55a86c0",
      "date": "8/20/2019, 1:21:30 PM",
      "weight": "73.02",
      "chest": "",
      "thigh": "",
      "upperarm": "",
      "waist": "",
      "hip": "",
      "trend": false
    }
  ]
}